Bot.py
simbots/Bot.py
simbots/Context.py
simbots/Entity.py
simbots/Intent.py
simbots/__init__.py
simbots/utils/__init__.py
simbots/utils/builtInEntities.py
simbots/utils/builtInIntents.py
simbots/utils/exceptions.py
simbots/utils/schemas.py
src/Bot.py
src/Context.py
src/Entity.py
src/Intent.py
src/__init__.py
simbots-0.0.28.dist-info/LICENCE.txt
simbots-0.0.28.dist-info/METADATA
simbots-0.0.28.dist-info/WHEEL
simbots-0.0.28.dist-info/top_level.txt
simbots-0.0.28.dist-info/RECORD
