Metadata-Version: 2.1
Name: simbots
Version: 0.0.28
Summary: Simple bots or Simbots is a library designed to create simple bots by computing Intents,Entities,Relations and Context .
Home-page: UNKNOWN
Author: Vaibhav Arora
Author-email: vaibhavaroradev@gmail.com
License: UNKNOWN
Platform: UNKNOWN
Classifier: Development Status :: 1 - Planning
Classifier: Operating System :: OS Independent
Classifier: License :: OSI Approved :: MIT License
Classifier: Programming Language :: Python :: 3
Requires-Dist: sklearn
Requires-Dist: objectpath
